README.md
setup.py
btcpy/__init__.py
btcpy/constants.py
btcpy/setup.py
btcpy/lib/__init__.py
btcpy/lib/base58.py
btcpy/lib/bech32.py
btcpy/lib/codecs.py
btcpy/lib/opcodes.py
btcpy/lib/parsing.py
btcpy/lib/types.py
btcpy/structs/__init__.py
btcpy/structs/address.py
btcpy/structs/block.py
btcpy/structs/crypto.py
btcpy/structs/hd.py
btcpy/structs/script.py
btcpy/structs/sig.py
btcpy/structs/transaction.py
chainside_btcpy_multi.egg-info/PKG-INFO
chainside_btcpy_multi.egg-info/SOURCES.txt
chainside_btcpy_multi.egg-info/dependency_links.txt
chainside_btcpy_multi.egg-info/not-zip-safe
chainside_btcpy_multi.egg-info/requires.txt
chainside_btcpy_multi.egg-info/top_level.txt
tests/__init__.py
tests/integration.py
tests/regtest.py
tests/unit.py