Metadata-Version: 2.1
Name: chainside-btcpy-multi
Version: 0.2.81
Summary: A Python3 SegWit-compliant library which provides tools to handle Bitcoin data structures in a simple fashion.
Home-page: https://github.com/chainside/btcpy
Author: chainside srl
Author-email: simone.bronzini@chainside.net
License: UNKNOWN
Download-URL: https://github.com/chainside/btcpy/archive/0.2.7.tar.gz
Keywords: bitcoin,blockchain,bitcoind,chainside
Platform: UNKNOWN
Requires-Python: >=3
Provides-Extra: develop
